gitcln/__init__.py
gitcln/__main__.py
gitcln/gitcln.py
gitcln-20.4.4.dist-info/LICENSE
gitcln-20.4.4.dist-info/METADATA
gitcln-20.4.4.dist-info/WHEEL
gitcln-20.4.4.dist-info/entry_points.txt
gitcln-20.4.4.dist-info/top_level.txt
gitcln-20.4.4.dist-info/RECORD
