Metadata-Version: 2.1
Name: gitcln
Version: 20.4.4
Summary: CLI tool aim to clean local git repository from .gitignore file(s)/folder(s).
Home-page: https://github.com/hadizakialqattan/gitcln
Author: Hadi Zaki Alqattan
Author-email: alqattanhadizaki@gmail.com
License: MIT License
Keywords: python,cli,tools,cleaner,git-tools
Platform: UNKNOWN
Classifier: License :: OSI Approved :: MIT License
Classifier: Programming Language :: Python
Classifier: Programming Language :: Python :: 3.6
Classifier: Programming Language :: Python :: 3.7
Classifier: Programming Language :: Python :: 3.8
Classifier: Programming Language :: Python :: 3.9
Classifier: Programming Language :: Python :: Implementation :: CPython
Classifier: Programming Language :: Python :: Implementation :: Jython
Classifier: Programming Language :: Python :: Implementation :: PyPy
Classifier: Topic :: Utilities
Requires-Python: >=3
